{"_id":{"$oid":"6953963b7b143f547a0931c0"},"ten":"Bài 1 - Vũ điệu niềm tin","slug":"bai-1-vu-dieu-niem-tin","mo_ta":"Hướng dẫn chi tiết các vũ điệu hoạt động tập thể trong Quân đội:","noi_dung":"<p style=\"text-align: center;\"><iframe frameborder=\"0\" height=\"480\" scrolling=\"no\" src=\"https://www.youtube.com/embed/JHM8r15QHP0?si=nfHi78G7ezWnr8LV\" width=\"640\"></iframe></p>","thu_tu":0,"tags":["cac-vu-dieu-trong-sinh-hoat-tap-the"],"photos":[],"attachments":[],"date_post":"2025-12-30 16:06:23","tin_moi":0,"id_user":{"$oid":"69533df1c2c912ac05084cde"},"updated_at":{"$date":"2026-01-01T02:32:53.086Z"},"created_at":{"$date":"2025-12-30T09:07:07.218Z"}}
{"_id":{"$oid":"69539684757d6e11a60926f2"},"ten":"Bài 2 - Vũ điệu quân dân","slug":"bai-2-vu-dieu-quan-dan","mo_ta":"Hướng dẫn chi tiết các vũ điệu tập thể trong Quân đội","noi_dung":"<p style=\"text-align: center;\"><iframe frameborder=\"0\" height=\"480\" scrolling=\"no\" src=\"https://www.youtube.com/embed/ZB80hf-6iIc?si=jxy769DpgxdzP8zV\" width=\"640\"></iframe></p>","thu_tu":0,"tags":["cac-vu-dieu-trong-sinh-hoat-tap-the"],"photos":[],"attachments":[],"date_post":"2025-12-30 16:07:34","tin_moi":0,"id_user":{"$oid":"69533df1c2c912ac05084cde"},"updated_at":{"$date":"2026-01-01T02:33:12.649Z"},"created_at":{"$date":"2025-12-30T09:08:20.067Z"}}
{"_id":{"$oid":"695396e054a822872100ceed"},"ten":"Bài 3 - Vũ Điệu Hành Quân","slug":"bai-3-vu-dieu-hanh-quan","mo_ta":"Hướng dẫn chi tiết các vũ điệu tập thể trong Quân đội","noi_dung":"<p style=\"text-align: center;\"><iframe frameborder=\"0\" height=\"480\" scrolling=\"no\" src=\"https://www.youtube.com/embed/p2qXe9IfjTk?si=l4FCt2CfzpEeYmCf\" width=\"640\"></iframe></p>","thu_tu":0,"tags":["cac-vu-dieu-trong-sinh-hoat-tap-the"],"photos":[],"attachments":[],"date_post":"2025-12-30 16:09:13","tin_moi":0,"id_user":{"$oid":"69533df1c2c912ac05084cde"},"updated_at":{"$date":"2026-01-01T02:33:34.275Z"},"created_at":{"$date":"2025-12-30T09:09:52.865Z"}}
{"_id":{"$oid":"6953971c50841405ef0ff632"},"ten":"Bài 4 - Vũ Điệu Lính trẻ","slug":"bai-4-vu-dieu-linh-tre","mo_ta":"Hướng dẫn chi tiết vũ điệu sinh hoạt tập thể của Quân đội năm 2023","noi_dung":"<p style=\"text-align: center;\"><iframe frameborder=\"0\" height=\"480\" scrolling=\"no\" src=\"https://www.youtube.com/embed/4-jX5SrBmZU?si=5961bsSgRFbL2ORQ\" width=\"640\"></iframe></p>","thu_tu":0,"tags":["cac-vu-dieu-trong-sinh-hoat-tap-the"],"photos":[],"attachments":[],"date_post":"2025-12-30 16:10:09","tin_moi":0,"id_user":{"$oid":"69533df1c2c912ac05084cde"},"updated_at":{"$date":"2026-01-01T02:33:52.716Z"},"created_at":{"$date":"2025-12-30T09:10:52.461Z"}}
{"_id":{"$oid":"6953979b757d6e11a60926f3"},"ten":"Bài 5 - Vũ điệu hòa bình","slug":"bai-5-vu-dieu-hoa-binh","mo_ta":"Hướng dẫn chi tiết vũ điệu sinh hoạt tập thể trong Quân đội năm 2023","noi_dung":"<p style=\"text-align: center;\"><iframe frameborder=\"0\" height=\"480\" scrolling=\"no\" src=\"https://www.youtube.com/embed/7-EojpWbV-Q?si=G1qavvQMHfOGiiSC\" width=\"640\"></iframe></p>","thu_tu":0,"tags":["cac-vu-dieu-trong-sinh-hoat-tap-the"],"photos":[],"attachments":[],"date_post":"2025-12-30 16:12:20","tin_moi":0,"id_user":{"$oid":"69533df1c2c912ac05084cde"},"updated_at":{"$date":"2026-01-01T02:34:04.563Z"},"created_at":{"$date":"2025-12-30T09:12:59.326Z"}}
{"_id":{"$oid":"695399548e95c991830d3f3a"},"ten":"ƯỚC MƠ CHIẾN SĨ","slug":"uoc-mo-chien-si","mo_ta":"ƯỚC MƠ CHIẾN SĨ - BẢN CHUẨN TỔNG CỤC CHÍNH TRỊ - KARAOKE BÀI HÁT QUY ĐỊNH BEAT | KHÔNG LỜI","noi_dung":"<p style=\"text-align: center;\"><iframe frameborder=\"0\" height=\"480\" scrolling=\"no\" src=\"https://www.youtube.com/embed/snUXcGavNK8?si=4u8wK8NbOVQF9-J6\" width=\"640\"></iframe></p>","thu_tu":0,"tags":["15-bai-quy-dinh"],"photos":[],"attachments":[],"date_post":"2025-12-30 16:19:44","tin_moi":0,"id_user":{"$oid":"69533df1c2c912ac05084cde"},"updated_at":{"$date":"2026-01-01T02:27:19.319Z"},"created_at":{"$date":"2025-12-30T09:20:20.035Z"}}
{"_id":{"$oid":"69539988757d6e11a60926f4"},"ten":"HÁT MÃI KHÚC QUÂN HÀNH","slug":"hat-mai-khuc-quan-hanh","mo_ta":"HÁT MÃI KHÚC QUÂN HÀNH - BẢN CHUẨN TỔNG CỤC CHÍNH TRỊ - KARAOKE BÀI HÁT QUY ĐỊNH BEAT | KHÔNG LỜI","noi_dung":"<p style=\"text-align: center;\"><iframe frameborder=\"0\" height=\"480\" scrolling=\"no\" src=\"https://www.youtube.com/embed/wn3n6n_fcc0?si=CGO2-LSlfyLLcYNT\" width=\"640\"></iframe></p>","thu_tu":0,"tags":["15-bai-quy-dinh"],"photos":[],"attachments":[],"date_post":"2025-12-30 16:20:43","tin_moi":0,"id_user":{"$oid":"69533df1c2c912ac05084cde"},"updated_at":{"$date":"2026-01-01T02:27:06.028Z"},"created_at":{"$date":"2025-12-30T09:21:12.672Z"}}
{"_id":{"$oid":"695399ba54a822872100ceee"},"ten":"TỔ QUỐC TRONG TIM","slug":"to-quoc-trong-tim","mo_ta":"TỔ QUỐC TRONG TIM - BẢN CHUẨN TỔNG CỤC CHÍNH TRỊ - KARAOKE BÀI HÁT QUY ĐỊNH BEAT","noi_dung":"<p style=\"text-align: center;\"><iframe frameborder=\"0\" height=\"480\" scrolling=\"no\" src=\"https://www.youtube.com/embed/T2vmb30hFD8?si=U2M-eN5V-UZlYgAC\" width=\"640\"></iframe></p>","thu_tu":0,"tags":["15-bai-quy-dinh"],"photos":[],"attachments":[],"date_post":"2025-12-30 16:21:32","tin_moi":0,"id_user":{"$oid":"69533df1c2c912ac05084cde"},"updated_at":{"$date":"2026-01-01T02:28:17.269Z"},"created_at":{"$date":"2025-12-30T09:22:02.809Z"}}
{"_id":{"$oid":"695399ef50841405ef0ff633"},"ten":"THANH NIÊN LÀM THEO LỜI BÁC","slug":"thanh-nien-lam-theo-loi-bac","mo_ta":"THANH NIÊN LÀM THEO LỜI BÁC - BẢN CHUẨN TỔNG CỤC CHÍNH TRỊ - KARAOKE BÀI HÁT QUY ĐỊNH BEAT","noi_dung":"<p style=\"text-align: center;\"><iframe frameborder=\"0\" height=\"480\" scrolling=\"no\" src=\"https://www.youtube.com/embed/8aiAU_QN7qc?si=gDsN9hcviP7htoKp\" width=\"640\"></iframe></p>","thu_tu":0,"tags":["15-bai-quy-dinh"],"photos":[],"attachments":[],"date_post":"2025-12-30 16:22:23","tin_moi":0,"id_user":{"$oid":"69533df1c2c912ac05084cde"},"updated_at":{"$date":"2026-01-01T02:26:54.366Z"},"created_at":{"$date":"2025-12-30T09:22:55.897Z"}}
{"_id":{"$oid":"69539a1ce08e4f2a8e015a80"},"ten":"BÁC ĐANG CÙNG CHÚNG CHÁU HÀNH QUÂN","slug":"bac-dang-cung-chung-chau-hanh-quan","mo_ta":"BÁC ĐANG CÙNG CHÚNG CHÁU HÀNH QUÂN - BẢN CHUẨN TỔNG CỤC CHÍNH TRỊ - KARAOKE BÀI HÁT QUY ĐỊNH BEAT","noi_dung":"<p style=\"text-align: center;\"><iframe frameborder=\"0\" height=\"480\" scrolling=\"no\" src=\"https://www.youtube.com/embed/M1pI9Q80q90?si=lgcpu0DQV3qnq7k2\" width=\"640\"></iframe></p>","thu_tu":0,"tags":["15-bai-quy-dinh"],"photos":[],"attachments":[],"date_post":"2025-12-30 16:23:12","tin_moi":0,"id_user":{"$oid":"69533df1c2c912ac05084cde"},"updated_at":{"$date":"2026-01-01T02:31:21.598Z"},"created_at":{"$date":"2025-12-30T09:23:40.096Z"}}
{"_id":{"$oid":"69539a518127863a550c32d4"},"ten":"CUỘC ĐỜI VẪN ĐẸP SAO","slug":"cuoc-doi-van-dep-sao","mo_ta":"CUỘC ĐỜI VẪN ĐẸP SAO - BẢN CHUẨN TỔNG CỤC CHÍNH TRỊ - KARAOKE BÀI HÁT QUY ĐỊNH BEAT | KHÔNG LỜI","noi_dung":"<p style=\"text-align: center;\"><iframe frameborder=\"0\" height=\"480\" scrolling=\"no\" src=\"https://www.youtube.com/embed/V-3qUQ3j7TI?si=n-PFVj9H74WDlZAT\" width=\"640\"></iframe></p>","thu_tu":0,"tags":["15-bai-quy-dinh"],"photos":[],"attachments":[],"date_post":"2025-12-30 16:24:11","tin_moi":0,"id_user":{"$oid":"69533df1c2c912ac05084cde"},"updated_at":{"$date":"2026-01-01T02:31:37.099Z"},"created_at":{"$date":"2025-12-30T09:24:33.525Z"}}
{"_id":{"$oid":"69539ad85b90d9b42203ab8c"},"ten":"TRÁI TIM CHIẾN SĨ","slug":"trai-tim-chien-si","mo_ta":"TRÁI TIM CHIẾN SĨ - BẢN CHUẨN TỔNG CỤC CHÍNH TRỊ - KARAOKE BÀI HÁT QUY ĐỊNH BEAT | KHÔNG LỜI","noi_dung":"<p style=\"text-align: center;\"><iframe frameborder=\"0\" height=\"480\" scrolling=\"no\" src=\"https://www.youtube.com/embed/YuieT-eB9X8?si=pSI_KYqRBIxV6QTg\" width=\"640\"></iframe></p>","thu_tu":0,"tags":["15-bai-quy-dinh"],"photos":[],"attachments":[],"date_post":"2025-12-30 16:26:14","tin_moi":0,"id_user":{"$oid":"69533df1c2c912ac05084cde"},"updated_at":{"$date":"2026-01-01T02:26:35.666Z"},"created_at":{"$date":"2025-12-30T09:26:48.311Z"}}
{"_id":{"$oid":"69539b0e757d6e11a60926f5"},"ten":"NHƯ CÓ BÁC TRONG NGÀY VUI ĐẠI THẮNG","slug":"nhu-co-bac-trong-ngay-vui-dai-thang","mo_ta":"NHƯ CÓ BÁC TRONG NGÀY VUI ĐẠI THẮNG - BẢN CHUẨN TỔNG CỤC CHÍNH TRỊ - KARAOKE BÀI HÁT QUY ĐỊNH BEAT","noi_dung":"<p style=\"text-align: center;\"><iframe frameborder=\"0\" height=\"480\" scrolling=\"no\" src=\"https://www.youtube.com/embed/4YX7tuGx6IQ?si=tigq8Iut7lClvgWG\" width=\"640\"></iframe></p>","thu_tu":0,"tags":["15-bai-quy-dinh"],"photos":[],"attachments":[],"date_post":"2025-12-30 16:27:09","tin_moi":0,"id_user":{"$oid":"69533df1c2c912ac05084cde"},"updated_at":{"$date":"2026-01-01T02:31:58.073Z"},"created_at":{"$date":"2025-12-30T09:27:42.148Z"}}
{"_id":{"$oid":"69539b348127863a550c32d5"},"ten":"TIẾN BƯỚC DƯỚI QUÂN KỲ","slug":"tien-buoc-duoi-quan-ky","mo_ta":"TIẾN BƯỚC DƯỚI QUÂN KỲ - BẢN CHUẨN TỔNG CỤC CHÍNH TRỊ - KARAOKE BÀI HÁT QUY ĐỊNH BEAT | KHÔNG LỜI","noi_dung":"<p style=\"text-align: center;\"><iframe frameborder=\"0\" height=\"480\" scrolling=\"no\" src=\"https://www.youtube.com/embed/dGqUlBgNXFk?si=r2ipCjozONQE0WM6\" width=\"640\"></iframe></p>","thu_tu":0,"tags":["15-bai-quy-dinh"],"photos":[],"attachments":[],"date_post":"2025-12-30 16:27:54","tin_moi":0,"id_user":{"$oid":"69533df1c2c912ac05084cde"},"updated_at":{"$date":"2026-01-01T02:26:10.548Z"},"created_at":{"$date":"2025-12-30T09:28:20.915Z"}}
{"_id":{"$oid":"69539b5d5b90d9b42203ab8d"},"ten":"GIẢI PHÓNG ĐIỆN BIÊN","slug":"giai-phong-dien-bien","mo_ta":"GIẢI PHÓNG ĐIỆN BIÊN - BẢN CHUẨN TỔNG CỤC CHÍNH TRỊ - KARAOKE BÀI HÁT QUY ĐỊNH BEAT | KHÔNG LỜI","noi_dung":"<p style=\"text-align: center;\"><iframe frameborder=\"0\" height=\"480\" scrolling=\"no\" src=\"https://www.youtube.com/embed/1P6XiikwZoM?si=VOAdX8iQrNz3_tlr\" width=\"640\"></iframe></p>","thu_tu":0,"tags":["15-bai-quy-dinh"],"photos":[],"attachments":[],"date_post":"2025-12-30 16:28:31","tin_moi":0,"id_user":{"$oid":"69533df1c2c912ac05084cde"},"updated_at":{"$date":"2026-01-01T02:25:35.701Z"},"created_at":{"$date":"2025-12-30T09:29:01.614Z"}}
{"_id":{"$oid":"69539b860ba519f2c60ea102"},"ten":"CA NGỢI HỒ CHỦ TỊCH","slug":"ca-ngoi-ho-chu-tich","mo_ta":"CA NGỢI HỒ CHỦ TỊCH - BẢN CHUẨN TỔNG CỤC CHÍNH TRỊ - KARAOKE BÀI HÁT QUY ĐỊNH BEAT | KHÔNG LỜI","noi_dung":"<p style=\"text-align: center;\"><iframe frameborder=\"0\" height=\"480\" scrolling=\"no\" src=\"https://www.youtube.com/embed/Gadf4lpaUkM?si=kiazZfaw8AY3P4AB\" width=\"640\"></iframe></p>","thu_tu":0,"tags":["15-bai-quy-dinh"],"photos":[],"attachments":[],"date_post":"2025-12-30 16:29:15","tin_moi":0,"id_user":{"$oid":"69533df1c2c912ac05084cde"},"updated_at":{"$date":"2026-01-01T02:25:17.955Z"},"created_at":{"$date":"2025-12-30T09:29:42.698Z"}}
{"_id":{"$oid":"69539bae51cd0f495903d74d"},"ten":"CHÀO MỪNG ĐẢNG CỘNG SẢN VIỆT NAM","slug":"chao-mung-dang-cong-san-viet-nam","mo_ta":"CHÀO MỪNG ĐẢNG CỘNG SẢN VIỆT NAM - BẢN CHUẨN TỔNG CỤC CHÍNH TRỊ - KARAOKE BÀI HÁT QUY ĐỊNH KHÔNG LỜI","noi_dung":"<p style=\"text-align: center;\"><iframe frameborder=\"0\" height=\"480\" scrolling=\"no\" src=\"https://www.youtube.com/embed/Wlnt0adMNQw?si=nJDqjHyWr-2nsFEz\" width=\"640\"></iframe></p>","thu_tu":0,"tags":["15-bai-quy-dinh"],"photos":[],"attachments":[],"date_post":"2025-12-30 16:29:53","tin_moi":0,"id_user":{"$oid":"69533df1c2c912ac05084cde"},"updated_at":{"$date":"2026-01-01T02:24:51.618Z"},"created_at":{"$date":"2025-12-30T09:30:22.177Z"}}
{"_id":{"$oid":"69539bdd7b143f547a0931c1"},"ten":"VÌ NHÂN DÂN QUÊN MÌNH","slug":"vi-nhan-dan-quen-minh","mo_ta":"VÌ NHÂN DÂN QUÊN MÌNH - BẢN CHUẨN TỔNG CỤC CHÍNH TRỊ - KARAOKE BÀI HÁT QUY ĐỊNH BEAT | KHÔNG LỜI","noi_dung":"<p style=\"text-align: center;\"><iframe frameborder=\"0\" height=\"480\" scrolling=\"no\" src=\"https://www.youtube.com/embed/Lz6FoGfo8Cc?si=DfYbX23zvj0DIoH3\" width=\"640\"></iframe></p>","thu_tu":0,"tags":["15-bai-quy-dinh"],"photos":[],"attachments":[],"date_post":"2025-12-30 16:30:44","tin_moi":0,"id_user":{"$oid":"69533df1c2c912ac05084cde"},"updated_at":{"$date":"2026-01-01T02:24:01.424Z"},"created_at":{"$date":"2025-12-30T09:31:09.981Z"}}
{"_id":{"$oid":"69539c0392f0721f160ec59b"},"ten":"KARAOKE TIẾN QUÂN CA","slug":"karaoke-tien-quan-ca","mo_ta":"KARAOKE TIẾN QUÂN CA - BẢN CHUẨN TỔNG CỤC CHÍNH TRỊ - KARAOKE BÀI HÁT QUY ĐỊNH BEAT | KHÔNG LỜI","noi_dung":"<p style=\"text-align: center;\"><iframe frameborder=\"0\" height=\"480\" scrolling=\"no\" src=\"https://www.youtube.com/embed/wIXyXqeDgc4?si=_5SGSRza3pED33sD\" width=\"640\"></iframe></p>","thu_tu":0,"tags":["15-bai-quy-dinh"],"photos":[],"attachments":[],"date_post":"2025-12-30 16:31:20","tin_moi":0,"id_user":{"$oid":"69533df1c2c912ac05084cde"},"updated_at":{"$date":"2026-01-01T02:23:42.416Z"},"created_at":{"$date":"2025-12-30T09:31:47.626Z"}}
{"_id":{"$oid":"6954828b54a822872100ceef"},"ten":"Tham quan bảo tàng lịch sử quân sự Việt Nam","slug":"tham-quan-bao-tang-lich-su-quan-su-viet-nam","mo_ta":"Tham quan bảo tàng lịch sử quân sự Việt Nam","noi_dung":"<p>Click v&agrave; link để xem:&nbsp;<a href=\"https://vr360.yoolife.vn/bao-tang-lich-su-quan-su-viet-nam-zmuseumc118u26724\" target=\"_blank\"><span style=\"color:#c0392b;\"><strong>https://vr360.yoolife.vn/bao-tang-lich-su-quan-su-viet-nam-zmuseumc118u26724</strong></span></a></p>\r\n\r\n<p>&nbsp;</p>","thu_tu":0,"tags":["giao-duc-truyen-thong","truyen-thong-quan-doi"],"photos":[],"attachments":[],"date_post":"2025-12-31 08:53:09","tin_moi":0,"id_user":{"$oid":"69533df1c2c912ac05084cde"},"updated_at":{"$date":"2025-12-31T01:55:23.707Z"},"created_at":{"$date":"2025-12-31T01:55:23.707Z"}}
{"_id":{"$oid":"6954d48054a822872100cef1"},"ten":"Quy chế 775/QĐ-CT ngày 12/5/2025 của Tổng Cục Chính trị Quân đội nhân dân Việt Nam","slug":"quy-che-cong-tac-quan-ly-tu-tuong-quan-nhan-nam-va-dinh-huong-du-luan-trong-quan-doi-nhan-dan-viet-nam","mo_ta":"Quy chế 775/QĐ-CT ngày 12/5/2025 của Tổng Cục Chính trị Quân đội nhân dân Việt Nam","noi_dung":"<p>Về c&ocirc;ng t&aacute;c quản l&yacute; tư tưởng qu&acirc;n nh&acirc;n; nắm v&agrave; định hướng dư luận trong Qu&acirc;n đội nh&acirc;n d&acirc;n Việt Nam</p>","thu_tu":0,"tags":["quy-che-nam-quan-ly-tu-tuong"],"photos":[],"attachments":[{"aliasname":"20251231144051_6954d383bf062.pdf","filename":"QUY CHẾ 775 VỀ CÔNG TÁC QUẢN LÝ TƯ TƯỞNG QUÂN NHÂN.pdf","title":"QUY CHẾ 775 VỀ CÔNG TÁC QUẢN LÝ TƯ TƯỞNG QUÂN NHÂN.pdf","size":"591378","type":"pdf"}],"date_post":"2025-12-31 14:38:52","tin_moi":0,"id_user":{"$oid":"69533df1c2c912ac05084cde"},"updated_at":{"$date":"2025-12-31T07:45:04.871Z"},"created_at":{"$date":"2025-12-31T07:45:04.871Z"}}
{"_id":{"$oid":"6954d9f85b90d9b42203ab8f"},"ten":"100 TÌNH HUỐNG TƯ TƯỞNG","slug":"100-tinh-huong-tu-tuong","mo_ta":"Tập 1","noi_dung":"<p>T&igrave;nh huống tư tưởng c&oacute; thể nảy sinh ở đơn vị cơ sở v&agrave; gợi &yacute; biện ph&aacute;p&nbsp;xử l&yacute;</p>","thu_tu":0,"tags":["100-tinh-huong-tu-tuong"],"photos":[],"attachments":[{"aliasname":"20251231150624_6954d9800b9e4.pdf","filename":"100 TÌNH HUỐNG TƯ TƯỞNG  - TẬP 1.pdf","title":"100 TÌNH HUỐNG TƯ TƯỞNG  - TẬP 1.pdf","size":"1031138","type":"pdf"}],"date_post":"2025-12-31 15:02:35","tin_moi":0,"id_user":{"$oid":"69533df1c2c912ac05084cde"},"updated_at":{"$date":"2025-12-31T08:08:24.445Z"},"created_at":{"$date":"2025-12-31T08:08:24.445Z"}}
{"_id":{"$oid":"6954de05e08e4f2a8e015a84"},"ten":"100 TÌNH HUỐNG TƯ TƯỞNG - T3","slug":"100-tinh-huong-tu-tuong-t3","mo_ta":"TẬP 3","noi_dung":"<p>100 t&igrave;nh huống tư tưởng c&oacute; thể nảy sinh ở đơn vị cơ sở v&agrave; gợi &yacute; biện ph&aacute;p&nbsp;xử l&yacute; - Tập 3</p>","thu_tu":0,"tags":["100-tinh-huong-tu-tuong"],"photos":[],"attachments":[{"aliasname":"20251231152536_6954de0001c5f.pdf","filename":"100 TÌNH HUỐNG TƯ TƯỞNG - TẬP 3.pdf","title":"100 TÌNH HUỐNG TƯ TƯỞNG - TẬP 3.pdf","size":"967342","type":"pdf"}],"date_post":"2025-12-31 15:12:40","tin_moi":0,"id_user":{"$oid":"69533df1c2c912ac05084cde"},"updated_at":{"$date":"2025-12-31T08:25:41.005Z"},"created_at":{"$date":"2025-12-31T08:25:41.005Z"}}
{"_id":{"$oid":"6955d73e0b0e0369f00ab65d"},"ten":"ĐỀ CƯƠNG TUYÊN TRUYỀN 80 NĂM NGÀY THÀNH LẬP QUÂN ĐỘI NHÂN DÂN VIỆT NAM (22/12/1944 - 22/12/2024) VÀ 35 NĂM NGÀY HỘI QUỐC PHÒNG TOÀN DÂN (22/12/1989 - 22/12/2024)","slug":"de-cuong","mo_ta":"Tài liệu do Ban Tuyên giáo và Dân vận trung ương; Tổng Cục Chính trị QĐND Việt Nam biên soạn","noi_dung":"<p>&ldquo;Qu&acirc;n đội ta trung với Đảng, hiếu với d&acirc;n, sẵn s&agrave;ng chiến đấu hy sinh v&igrave; độc lập, tự do của Tổ quốc, v&igrave; chủ nghĩa x&atilde; hội. Nhiệm vụ n&agrave;o cũng ho&agrave;n th&agrave;nh, kh&oacute; khăn n&agrave;o cũng vượt qua, kẻ th&ugrave; n&agrave;o cũng đ&aacute;nh thắng&rdquo;</p>","thu_tu":0,"tags":["de-cuong-tuyen-truyen"],"photos":[],"attachments":[{"aliasname":"20260101090617_6955d699eab33.pdf","filename":"ĐỀ CƯƠNG TUYÊN TRUYỀN 80 NĂM NGÀY THÀNH LẬP QUÂN ĐỘI NHÂN DÂN VIỆT NAM VÀ 35 NĂM NGÀY HỘI QUỐC PHÒNG TOÀN DÂN.pdf","title":"ĐỀ CƯƠNG TUYÊN TRUYỀN 80 NĂM NGÀY THÀNH LẬP QUÂN ĐỘI NHÂN DÂN VIỆT NAM VÀ 35 NĂM NGÀY HỘI QUỐC PHÒNG TOÀN DÂN.pdf","size":"402300","type":"pdf"}],"date_post":"2026-01-01 09:05:02","tin_moi":0,"id_user":{"$oid":"69533df1c2c912ac05084cde"},"updated_at":{"$date":"2026-01-01T02:13:12.347Z"},"created_at":{"$date":"2026-01-01T02:09:02.153Z"}}
{"_id":{"$oid":"6955da0b8e95c991830d3f3b"},"ten":"Tài liệu tuyên truyền Kỷ niệm 80 năm Ngày thành lập Quân đội nhân dân Việt Nam (22-12-1944/ 22-12-2024) và 35 năm Ngày hội Quốc phòng toàn dân (22-12-1989/ 22-12-2024)","slug":"tai-lieu-tuyen-truyen-ky-niem-80-nam-ngay-thanh-lap-qdnd-viet-nam-va-36-nam-ngay-hoi","mo_ta":"Tài liệu do Tổng cục Chính trị QĐND Việt Nam biên soạn","noi_dung":"<p><span style=\"font-size:10px;\">T&agrave;i liệu nhằm &ocirc;n lại truyền thống vẻ vang của Qu&acirc;n đội nh&acirc;n d&acirc;n Việt Nam anh h&ugrave;ng, một đội qu&acirc;n c&aacute;ch mạng đ&atilde; lập nhiều chiến c&ocirc;ng vang dội, rạng ngời th&agrave;nh t&iacute;ch, son sắt lời thề tận trung với Đảng, tận hiếu với d&acirc;n, nhiệm vụ n&agrave;o cũng ho&agrave;n th&agrave;nh, kh&oacute; khăn n&agrave;o cũng vượt qua, kẻ th&ugrave; n&agrave;o cũng đ&aacute;nh thắng. Qua đ&oacute;, khơi dậy niềm tự h&agrave;o, tự t&ocirc;n d&acirc;n tộc, ph&aacute;t huy chủ nghĩa anh h&ugrave;ng c&aacute;ch mạng, n&acirc;ng cao l&ograve;ng y&ecirc;u nước, 6 y&ecirc;u chủ nghĩa x&atilde; hội, &yacute; ch&iacute; quật cường, &yacute; thức tự lực, tự cường vượt qua mọi kh&oacute; khăn, thử th&aacute;ch; ra sức x&acirc;y dựng nền quốc ph&ograve;ng to&agrave;n d&acirc;n vững mạnh, x&acirc;y dựng thế trận quốc ph&ograve;ng to&agrave;n d&acirc;n gắn với thế trận an ninh nh&acirc;n d&acirc;n ng&agrave;y c&agrave;ng vững chắc, x&acirc;y dựng Qu&acirc;n đội nh&acirc;n d&acirc;n Việt Nam c&aacute;ch mạng, ch&iacute;nh quy, tinh nhuệ, từng bước hiện đại, đ&aacute;p ứng y&ecirc;u cầu, nhiệm vụ bảo vệ Tổ quốc Việt Nam x&atilde; hội chủ nghĩa trong thời kỳ mới.</span></p>","thu_tu":0,"tags":["de-cuong-tuyen-truyen"],"photos":[],"attachments":[{"aliasname":"20260101092056_6955da082468c.pdf","filename":"Tai lieu tuyen truyen 80 nam thanh lap QDNDVN.pdf","title":"Tai lieu tuyen truyen 80 nam thanh lap QDNDVN.pdf","size":"1294627","type":"pdf"}],"date_post":"2026-01-01 09:14:59","tin_moi":0,"id_user":{"$oid":"69533df1c2c912ac05084cde"},"updated_at":{"$date":"2026-01-01T02:20:59.027Z"},"created_at":{"$date":"2026-01-01T02:20:59.027Z"}}
{"_id":{"$oid":"6955e0768e95c991830d3f3c"},"ten":"Thái Uý Lý Thường Kiệt - Đại Chiến Ung Châu Thành","slug":"thai-uy-ly-thuong-kiet-dai-chien-ung-chau-thanh","mo_ta":"Phim hoạt hình lịch sử","noi_dung":"<p style=\"text-align: center;\"><a href=\"https://www.youtube.com/watch?v=7aWhypk7W34\"><iframe frameborder=\"0\" height=\"480\" scrolling=\"no\" src=\"https://www.youtube.com/embed/7aWhypk7W34?si=lAlZs1TQlEeZNcJE\" width=\"640\"></iframe></a></p>\r\n\r\n<p><a href=\"https://www.youtube.com/watch?v=7aWhypk7W34\">https://www.youtube.com/watch?v=7aWhypk7W34</a></p>","thu_tu":0,"tags":["truyen-thong-dan-toc"],"photos":[],"attachments":[],"date_post":"2026-01-01 09:35:06","tin_moi":0,"id_user":{"$oid":"69533df1c2c912ac05084cde"},"updated_at":{"$date":"2026-01-05T01:45:09.342Z"},"created_at":{"$date":"2026-01-01T02:48:22.984Z"}}
{"_id":{"$oid":"69567afdcf0664121806272b"},"ten":"BÀI 7 NỘI DUNG CƠ BẢN CỦA CÔNG ƯỚC LIÊN HỢP QUỐC VỀ LUẬT BIỂN NĂM 1982 VÀ LUẬT BIỂN VIỆT NAM, TUYÊN BỐ ỨNG XỬ CÁC BÊN Ở BIỂN ĐÔNG","slug":"bai-7-noi-dung-co-ban-cua-cong-uoc-lien-hop-quoc-ve-luat-bien-nam-1982-va-luat-bien-viet-nam-tuyen-bo-ung-xu-cac-ben-o-bien-dong","mo_ta":"Bài 7","noi_dung":"<p>NỘI DUNG CƠ BẢN CỦA C&Ocirc;NG ƯỚC LI&Ecirc;N HỢP QUỐC VỀ LUẬT BIỂN NĂM 1982 V&Agrave; LUẬT BIỂN VIỆT NAM, TUY&Ecirc;N BỐ ỨNG XỬ C&Aacute;C B&Ecirc;N Ở BIỂN Đ&Ocirc;NG</p>","thu_tu":0,"tags":["bai-giang-dqtv"],"photos":[],"attachments":[{"aliasname":"20260101204941_69567b752ebee.pdf","filename":"7CONGUOCLHQ.pdf","title":"7CONGUOCLHQ.pdf","size":"509227","type":"pdf"}],"date_post":"2026-01-01 20:46:46","tin_moi":0,"id_user":{"$oid":"69533df1c2c912ac05084cde"},"updated_at":{"$date":"2026-01-01T13:49:43.365Z"},"created_at":{"$date":"2026-01-01T13:47:41.519Z"}}
{"_id":{"$oid":"69567be1cf0664121806272c"},"ten":"BÀI 11: PHÒNG, CHỐNG ÂM MƯU, THỦ ĐOẠN “DIỄN BIẾN HÒA BÌNH” CỦA CÁC THẾ LỰC THÙ ĐỊCH CHỐNG PHÁ CÁCH MẠNG VIỆT NAM HIỆN NAY","slug":"bai-11-phong-chong-am-muu-thu-doan-dien-bien-hoa-binh-cua-cac-the-luc-thu-dich-chong-pha-cach-mang-viet-nam-hien-nay","mo_ta":"BÀI 11","noi_dung":"<p>PH&Ograve;NG, CHỐNG &Acirc;M MƯU, THỦ ĐOẠN &ldquo;DIỄN BIẾN H&Ograve;A B&Igrave;NH&rdquo; CỦA C&Aacute;C THẾ LỰC TH&Ugrave; ĐỊCH CHỐNG PH&Aacute; C&Aacute;CH MẠNG VIỆT NAM HIỆN NAY</p>","thu_tu":0,"tags":["bai-giang-dqtv"],"photos":[],"attachments":[{"aliasname":"20260101205125_69567bddc8526.pdf","filename":"11DIEN BIEN HOA BINH.pdf","title":"11DIEN BIEN HOA BINH.pdf","size":"550038","type":"pdf"}],"date_post":"2026-01-01 20:50:36","tin_moi":0,"id_user":{"$oid":"69533df1c2c912ac05084cde"},"updated_at":{"$date":"2026-01-01T13:51:29.718Z"},"created_at":{"$date":"2026-01-01T13:51:29.718Z"}}
{"_id":{"$oid":"695721db51cd0f495903d752"},"ten":"LUẬT GIÁO DỤC QUỐC PHÒNG VÀ AN NINH","slug":"luat-giao-duc-quoc-phong-va-an-ninh","mo_ta":"LUẬT GIÁO DỤC QUỐC PHÒNG VÀ AN NINH","noi_dung":"<p style=\"text-align: justify;\"><span style=\"font-size:10px;\">Luật Gi&aacute;o dục quốc ph&ograve;ng v&agrave; an ninh số 30/2013/QH13 ng&agrave;y 19 th&aacute;ng 6 năm 2013 của Quốc hội, c&oacute; hiệu lực kể từ ng&agrave;y 01 th&aacute;ng 01 năm 2014, được sửa đổi, bổ sung bởi: 1. Luật số 35/2018/QH14 ng&agrave;y 20 th&aacute;ng 11 năm 2018 của Quốc hội sửa đổi, bổ sung một số điều của 37 luật c&oacute; li&ecirc;n quan đến quy hoạch, c&oacute; hiệu lực kể từ ng&agrave;y 01 th&aacute;ng 01 năm 2019; 2. Luật số 98/2025/QH15 ng&agrave;y 27 th&aacute;ng 6 năm 2025 của Quốc hội sửa đổi, bổ sung một số điều của 11 luật về qu&acirc;n sự, quốc ph&ograve;ng, c&oacute; hiệu lực kể từ ng&agrave;y 01 th&aacute;ng 7 năm 2025</span></p>","thu_tu":0,"tags":["mot-so-luat-co-ban"],"photos":[],"attachments":[{"aliasname":"20260102083937_695721d930935.pdf","filename":"Luật giáo dục QP&AN.pdf","title":"Luật giáo dục QP&AN.pdf","size":"862919","type":"pdf"}],"date_post":"2026-01-02 08:37:30","tin_moi":0,"id_user":{"$oid":"69533df1c2c912ac05084cde"},"updated_at":{"$date":"2026-01-02T01:39:39.322Z"},"created_at":{"$date":"2026-01-02T01:39:39.322Z"}}
{"_id":{"$oid":"6957225be08e4f2a8e015a85"},"ten":"LUẬT DÂN QUÂN TỰ VỆ","slug":"luat-dan-quan-tu-ve","mo_ta":"LUẬT DÂN QUÂN TỰ VỆ","noi_dung":"<p style=\"text-align: justify;\"><span style=\"font-size:10px;\">Luật D&acirc;n qu&acirc;n tự vệ số 48/2019/QH14 ng&agrave;y 22 th&aacute;ng 11 năm 2019 của Quốc hội, c&oacute; hiệu lực kể từ ng&agrave;y 01 th&aacute;ng 7 năm 2020, được sửa đổi, bổ sung bởi: Luật số 98/2025/QH15 ng&agrave;y 27 th&aacute;ng 6 năm 2025 của Quốc hội sửa đổi, bổ sung một số điều của 11 luật về qu&acirc;n sự, quốc ph&ograve;ng, c&oacute; hiệu lực kể từ ng&agrave;y 01 th&aacute;ng 7 năm 2025</span></p>","thu_tu":0,"tags":["van-ban-ve-dqtv"],"photos":[],"attachments":[{"aliasname":"20260102084145_695722596d330.pdf","filename":"Luật DQTV.pdf","title":"Luật DQTV.pdf","size":"1112502","type":"pdf"}],"date_post":"2026-01-02 08:40:48","tin_moi":0,"id_user":{"$oid":"69533df1c2c912ac05084cde"},"updated_at":{"$date":"2026-01-05T01:32:21.855Z"},"created_at":{"$date":"2026-01-02T01:41:47.005Z"}}
{"_id":{"$oid":"6957233de08e4f2a8e015a86"},"ten":"LUẬT LỰC LƯỢNG DỰ BỊ ĐỘNG VIÊN","slug":"luat-luc-luong-du-bi-dong-vien","mo_ta":"LUẬT LỰC LƯỢNG DỰ BỊ ĐỘNG VIÊN","noi_dung":"<p style=\"text-align: justify;\"><span style=\"font-size:10px;\">Luật Lực lượng dự bị động vi&ecirc;n số 53/2019/QH14 ng&agrave;y 26 th&aacute;ng 11 năm 2019 của Quốc hội, c&oacute; hiệu lực kể từ ng&agrave;y 01 th&aacute;ng 7 năm 2020, được sửa đổi, bổ sung bởi: Luật số 98/2025/QH15 ng&agrave;y 27 th&aacute;ng 6 năm 2025 của Quốc hội sửa đổi, bổ sung một số điều của 11 luật về qu&acirc;n sự, quốc ph&ograve;ng, c&oacute; hiệu lực kể từ ng&agrave;y 01 th&aacute;ng 7 năm 2025.</span></p>","thu_tu":0,"tags":["van-ban-ve-dqtv"],"photos":[],"attachments":[{"aliasname":"20260102084440_69572308757cd.pdf","filename":"Luật Lực lượng Dự bị động viên.pdf","title":"Luật Lực lượng Dự bị động viên.pdf","size":"1107882","type":"pdf"}],"date_post":"2026-01-02 08:43:15","tin_moi":0,"id_user":{"$oid":"69533df1c2c912ac05084cde"},"updated_at":{"$date":"2026-01-05T01:32:13.186Z"},"created_at":{"$date":"2026-01-02T01:45:33.171Z"}}
{"_id":{"$oid":"695730e692f0721f160ec59c"},"ten":"LUẬT PHÒNG THỦ DÂN SỰ","slug":"luat-phong-thu-dan-su","mo_ta":"LUẬT PHÒNG THỦ DÂN SỰ","noi_dung":"<p style=\"text-align: justify;\"><span style=\"font-size:10px;\">Luật Ph&ograve;ng thủ d&acirc;n sự số 18/2023/QH15 ng&agrave;y 20 th&aacute;ng 6 năm 2023 của Quốc hội, c&oacute; hiệu lực kể từ ng&agrave;y 01 th&aacute;ng 7 năm 2024, được sửa đổi, bổ sung bởi: Luật số 98/2025/QH15 ng&agrave;y 27 th&aacute;ng 6 năm 2025 của Quốc hội sửa đổi, bổ sung một số điều của 11 luật về qu&acirc;n sự, quốc ph&ograve;ng, c&oacute; hiệu lực kể từ ng&agrave;y 01 th&aacute;ng 7 năm 2025.</span></p>","thu_tu":0,"tags":["mot-so-luat-co-ban","cac-van-ban-ve-dqtv"],"photos":[],"attachments":[{"aliasname":"20260102094306_695730ba06cee.pdf","filename":"Luật Phòng thủ dân sự.pdf","title":"Luật Phòng thủ dân sự.pdf","size":"815994","type":"pdf"}],"date_post":"2026-01-02 09:41:42","tin_moi":0,"id_user":{"$oid":"69533df1c2c912ac05084cde"},"updated_at":{"$date":"2026-01-02T02:43:50.173Z"},"created_at":{"$date":"2026-01-02T02:43:50.173Z"}}
{"_id":{"$oid":"695b31a6757d6e11a60926f8"},"ten":"Tóm tắt lịch sử dân tộc Việt Nam","slug":"tom-tat-lich-su-dan-toc-viet-nam","mo_ta":"SƠ ĐỒ TƯ DUY","noi_dung":"<p>T&oacute;m tắt lịch sử d&acirc;n tộc Việt Nam</p>","thu_tu":0,"tags":["truyen-thong-dan-toc"],"photos":[],"attachments":[{"aliasname":"20260105103202_695b30b2d7a45.pdf","filename":"Lịch sử Việt Nam.pdf","title":"Lịch sử Việt Nam.pdf","size":"587368","type":"pdf"}],"date_post":"2026-01-05 10:31:04","tin_moi":0,"id_user":{"$oid":"69533df1c2c912ac05084cde"},"updated_at":{"$date":"2026-01-05T03:36:06.412Z"},"created_at":{"$date":"2026-01-05T03:36:06.412Z"}}
{"_id":{"$oid":"695b3370889b713845017103"},"ten":"Bài 5 Kết hợp kinh tế, văn hoá, xã hội, đối ngoại với QP,AN trong xây dựng và bảo vệ tổ quốc Việt Nam XHCN","slug":"bai-5-ket-hop-kinh-te-van-hoa-xa-hoi-doi-ngoai-voi-qpan-trong-xay-dung-va-bao-ve-to-quoc-viet-nam-xhcn","mo_ta":"Bài 5","noi_dung":"<p>Kết hợp kinh tế, văn ho&aacute;, x&atilde; hội, đối ngoại với QP,AN trong x&acirc;y dựng v&agrave; bảo vệ tổ quốc Việt Nam XHCN</p>","thu_tu":0,"tags":["bai-giang-dqtv"],"photos":[],"attachments":[{"aliasname":"20260105104341_695b336dc7883.pdf","filename":"5KETHOPKTVHXH VS QPAN..pdf","title":"5KETHOPKTVHXH VS QPAN..pdf","size":"528826","type":"pdf"}],"date_post":"2026-01-05 10:41:55","tin_moi":0,"id_user":{"$oid":"69533df1c2c912ac05084cde"},"updated_at":{"$date":"2026-01-05T03:43:44.9Z"},"created_at":{"$date":"2026-01-05T03:43:44.9Z"}}
{"_id":{"$oid":"695b34488127863a550c32da"},"ten":"Bài 3 Chủ nghĩa Mác Lênin, tư tưởng Hồ Chí Minh","slug":"bai-3-chu-nghia-mac-lenin-tu-tuong-ho-chi-minh","mo_ta":"Bài 3 Chủ nghĩa Mác Lênin, tư tưởng Hồ Chí Minh","noi_dung":"<p>&nbsp;Chủ nghĩa M&aacute;c L&ecirc;nin, tư tưởng Hồ Ch&iacute; Minh</p>","thu_tu":0,"tags":["bai-giang-dqtv"],"photos":[],"attachments":[{"aliasname":"20260105104718_695b3446dc564.pdf","filename":"3SODOTUDUY CN MAC LENIN..pdf","title":"3SODOTUDUY CN MAC LENIN..pdf","size":"506098","type":"pdf"}],"date_post":"2026-01-05 10:45:33","tin_moi":0,"id_user":{"$oid":"69533df1c2c912ac05084cde"},"updated_at":{"$date":"2026-01-05T03:47:20.955Z"},"created_at":{"$date":"2026-01-05T03:47:20.955Z"}}
{"_id":{"$oid":"695c58d79709dc3ea00d41bb"},"ten":"Bài 9 Quan điểm, chính sách dân tộc, tôn giáo của Đảng và nhà nước ta trong tình hình mới","slug":"bai-9-quan-diem-chinh-sach-dan-toc-ton-giao-cua-dang-va-nha-nuoc-ta-trong-tinh-hinh-moi","mo_ta":"Bài 9","noi_dung":"<p>Quan điểm, ch&iacute;nh s&aacute;ch d&acirc;n tộc, t&ocirc;n gi&aacute;o của Đảng v&agrave; nh&agrave; nước ta trong t&igrave;nh h&igrave;nh mới</p>","thu_tu":0,"tags":["bai-giang-dqtv"],"photos":[],"attachments":[{"aliasname":"20260106073532_695c58d4a10e3.pdf","filename":"9QUANDIEMCHINHSACH..pdf","title":"9QUANDIEMCHINHSACH..pdf","size":"443253","type":"pdf"}],"date_post":"2026-01-06 07:34:29","tin_moi":0,"id_user":{"$oid":"69533df1c2c912ac05084cde"},"updated_at":{"$date":"2026-01-06T00:35:35.157Z"},"created_at":{"$date":"2026-01-06T00:35:35.157Z"}}
{"_id":{"$oid":"695c5a9f0ba519f2c60ea106"},"ten":"Lịch sử hình thành và phát triển của lực lượng dân quân tự vệ","slug":"lich-su-hinh-thanh-va-phat-trien-cua-luc-luong-dan-quan-tu-ve","mo_ta":"Bài","noi_dung":"<p>Lịch sử h&igrave;nh th&agrave;nh v&agrave; ph&aacute;t triển của lực lượng d&acirc;n qu&acirc;n tự vệ</p>","thu_tu":0,"tags":["bai-giang-dqtv"],"photos":[],"attachments":[{"aliasname":"20260106074308_695c5a9c259f1.pdf","filename":"SODO TRUYEN THONG DQTV..pdf","title":"SODO TRUYEN THONG DQTV..pdf","size":"360783","type":"pdf"}],"date_post":"2026-01-06 07:42:17","tin_moi":0,"id_user":{"$oid":"69533df1c2c912ac05084cde"},"updated_at":{"$date":"2026-01-06T00:43:11.49Z"},"created_at":{"$date":"2026-01-06T00:43:11.49Z"}}
{"_id":{"$oid":"695c5bd254a822872100cef2"},"ten":"Bài 4 Quản lý, bảo vệ biên giới quốc gia nước CHXHCN Việt Nam trong tình hình mới","slug":"bai-4-quan-ly-bao-ve-bien-gioi-quoc-gia-nuoc-chxhcn-viet-nam-trong-tinh-hinh-moi","mo_ta":"Bài 4","noi_dung":"<p>&nbsp;Quản l&yacute;, bảo vệ bi&ecirc;n giới quốc gia nước CHXHCN Việt Nam trong t&igrave;nh h&igrave;nh mới</p>","thu_tu":0,"tags":["bai-giang-dqtv"],"photos":[],"attachments":[{"aliasname":"20260106074811_695c5bcb66071.pdf","filename":"4QUAN LY BIEN GIOI QUOC GIA..pdf","title":"4QUAN LY BIEN GIOI QUOC GIA..pdf","size":"600533","type":"pdf"}],"date_post":"2026-01-06 07:43:56","tin_moi":0,"id_user":{"$oid":"69533df1c2c912ac05084cde"},"updated_at":{"$date":"2026-01-06T00:48:18.125Z"},"created_at":{"$date":"2026-01-06T00:48:18.125Z"}}
{"_id":{"$oid":"695c5c99cf0664121806272d"},"ten":"Bài 6 Chiến lược phát triển bền vững kinh tế biển Việt Nam đến năm 2030, tầm nhìn đến năm 2045","slug":"bai-6-chien-luoc-phat-trien-ben-vung-kinh-te-bien-viet-nam-den-nam-2030-tam-nhin-den-nam-2045","mo_ta":"Bài 6","noi_dung":"<p>&nbsp;Chiến lược ph&aacute;t triển bền vững kinh tế biển Việt Nam đến năm 2030, tầm nh&igrave;n đến năm 2045</p>","thu_tu":0,"tags":["bai-giang-dqtv"],"photos":[],"attachments":[{"aliasname":"20260106075032_695c5c58098bc.pdf","filename":"6CHIEN LUOC PHAT TRIEN KINH TE BIEN..pdf","title":"6CHIEN LUOC PHAT TRIEN KINH TE BIEN..pdf","size":"512631","type":"pdf"}],"date_post":"2026-01-06 07:49:15","tin_moi":0,"id_user":{"$oid":"69533df1c2c912ac05084cde"},"updated_at":{"$date":"2026-01-06T00:51:37.69Z"},"created_at":{"$date":"2026-01-06T00:51:37.69Z"}}
{"_id":{"$oid":"695c5cbd54a822872100cef3"},"ten":"Bài 1 Nội dung cơ bản luật DQTV","slug":"bai-1-noi-dung-co-ban-luat-dqtv","mo_ta":"Bài 1","noi_dung":"<p>&nbsp;Nội dung cơ bản luật DQTV</p>","thu_tu":0,"tags":["bai-giang-dqtv"],"photos":[],"attachments":[{"aliasname":"20260106075211_695c5cbb3ed11.pdf","filename":"1NOI DUNG CO BAN CUA LUAT DQTV..pdf","title":"1NOI DUNG CO BAN CUA LUAT DQTV..pdf","size":"507532","type":"pdf"}],"date_post":"2026-01-06 07:51:42","tin_moi":0,"id_user":{"$oid":"69533df1c2c912ac05084cde"},"updated_at":{"$date":"2026-01-06T00:52:13.428Z"},"created_at":{"$date":"2026-01-06T00:52:13.428Z"}}
{"_id":{"$oid":"695c5d620ba519f2c60ea107"},"ten":"Bài 8 DQTV tham gia xây dựng nền quốc phòng toàn dân","slug":"bai-8-dqtv-tham-gia-xay-dung-nen-quoc-phong-toan-dan","mo_ta":"Bài 8","noi_dung":"<p>DQTV tham gia x&acirc;y dựng nền quốc ph&ograve;ng to&agrave;n d&acirc;n</p>","thu_tu":0,"tags":["bai-giang-dqtv"],"photos":[],"attachments":[{"aliasname":"20260106075351_695c5d1f753a0.pdf","filename":"8 DQTV THAM GIA XAY DUNG..pdf","title":"8 DQTV THAM GIA XAY DUNG..pdf","size":"535363","type":"pdf"}],"date_post":"2026-01-06 07:53:22","tin_moi":0,"id_user":{"$oid":"69533df1c2c912ac05084cde"},"updated_at":{"$date":"2026-01-06T00:54:58.236Z"},"created_at":{"$date":"2026-01-06T00:54:58.236Z"}}
{"_id":{"$oid":"695c5df092f0721f160ec59d"},"ten":"Bài 12 DQTV làm công tác vận động quần chúng","slug":"bai-12-dqtv-lam-cong-tac-van-dong-quan-chung","mo_ta":"Bài 12","noi_dung":"<p>DQTV l&agrave;m c&ocirc;ng t&aacute;c vận động quần ch&uacute;ng</p>","thu_tu":0,"tags":["bai-giang-dqtv"],"photos":[],"attachments":[],"date_post":"2026-01-06 07:54:59","tin_moi":0,"id_user":{"$oid":"69533df1c2c912ac05084cde"},"updated_at":{"$date":"2026-01-06T00:57:20.804Z"},"created_at":{"$date":"2026-01-06T00:57:20.804Z"}}
{"_id":{"$oid":"695c5ea4889b713845017105"},"ten":"Bài 2 Quan điểm của Đảng về đối tác, đối tượng","slug":"bai-2-quan-diem-cua-dang-ve-doi-tac-doi-tuong","mo_ta":"Bài 2","noi_dung":"<p>&nbsp;Quan điểm của Đảng về đối t&aacute;c, đối tượng</p>","thu_tu":0,"tags":["bai-giang-dqtv"],"photos":[],"attachments":[{"aliasname":"20260106080017_695c5ea1cc73a.pdf","filename":"2 DOI TAC DOI TUONG..pdf","title":"2 DOI TAC DOI TUONG..pdf","size":"485293","type":"pdf"}],"date_post":"2026-01-06 07:59:36","tin_moi":0,"id_user":{"$oid":"69533df1c2c912ac05084cde"},"updated_at":{"$date":"2026-01-06T01:00:20.657Z"},"created_at":{"$date":"2026-01-06T01:00:20.657Z"}}
{"_id":{"$oid":"695c5f4e92f0721f160ec59e"},"ten":"Bài 10 Đường lối, chính sách đối ngoại của Đảng, Nhà nước ta","slug":"bai-10-duong-loi-chinh-sach-doi-ngoai-cua-dang-nha-nuoc-ta","mo_ta":"Bài 10","noi_dung":"<p>Đường lối, ch&iacute;nh s&aacute;ch đối ngoại của Đảng, Nh&agrave; nước ta</p>","thu_tu":0,"tags":["bai-giang-dqtv"],"photos":[],"attachments":[{"aliasname":"20260106080308_695c5f4c85044.pdf","filename":"10DUONGLOI CHINHSACH DOI NGOAI..pdf","title":"10DUONGLOI CHINHSACH DOI NGOAI..pdf","size":"481099","type":"pdf"}],"date_post":"2026-01-06 08:02:27","tin_moi":0,"id_user":{"$oid":"69533df1c2c912ac05084cde"},"updated_at":{"$date":"2026-01-06T01:03:10.361Z"},"created_at":{"$date":"2026-01-06T01:03:10.361Z"}}
{"_id":{"$oid":"695c60739709dc3ea00d41bc"},"ten":"BÀI 2: QUẢN LÝ, BẢO VỆ BIÊN GIỚI QUỐC GIA NƯỚC CỘNG HÒA XÃ HỘI CHỦ NGHĨA VIỆT NAM TRONG TÌNH HÌNH MỚI","slug":"bai-2-quan-ly-bao-ve-bien-gioi-quoc-gia-nuoc-cong-hoa-xa-hoi-chu-nghia-viet-nam-trong-tinh-hinh-moi","mo_ta":"BÀI 2","noi_dung":"<p>QUẢN L&Yacute;, BẢO VỆ BI&Ecirc;N GIỚI QUỐC GIA NƯỚC CỘNG H&Ograve;A X&Atilde; HỘI CHỦ NGHĨA VIỆT NAM TRONG T&Igrave;NH H&Igrave;NH MỚI</p>","thu_tu":0,"tags":["bai-giang-hsq-bs"],"photos":[],"attachments":[{"aliasname":"20260106080753_695c606905217.pdf","filename":"Sơ đồ chữ bài 2.pdf","title":"Sơ đồ chữ bài 2.pdf","size":"467590","type":"pdf"}],"date_post":"2026-01-06 08:06:01","tin_moi":0,"id_user":{"$oid":"69533df1c2c912ac05084cde"},"updated_at":{"$date":"2026-01-06T01:09:20.931Z"},"created_at":{"$date":"2026-01-06T01:08:03.22Z"}}
{"_id":{"$oid":"695c60f7e08e4f2a8e015a88"},"ten":"BÀI 4 NỘI DUNG CƠ BẢN CỦA CHIẾN LƯỢC PHÁT TRIỂN BỀN VỮNG KINH TẾ BIỂN VIỆT NAM ĐẾN NĂM 2030, TẦM NHÌN ĐẾN NĂM 2045","slug":"bai-4","mo_ta":"BÀI 4","noi_dung":"<p>NỘI DUNG CƠ BẢN CỦA CHIẾN LƯỢC PH&Aacute;T TRIỂN BỀN VỮNG KINH TẾ BIỂN VIỆT NAM ĐẾN NĂM 2030, TẦM NH&Igrave;N ĐẾN NĂM 2045</p>","thu_tu":0,"tags":["bai-giang-hsq-bs"],"photos":[],"attachments":[{"aliasname":"20260106081013_695c60f596123.pdf","filename":"Sơ đồ chữ bài 4.pdf","title":"Sơ đồ chữ bài 4.pdf","size":"583655","type":"pdf"}],"date_post":"2026-01-06 08:09:43","tin_moi":0,"id_user":{"$oid":"69533df1c2c912ac05084cde"},"updated_at":{"$date":"2026-01-06T01:10:35.213Z"},"created_at":{"$date":"2026-01-06T01:10:15.115Z"}}
{"_id":{"$oid":"695c61f354a822872100cef4"},"ten":"BÀI 5: TĂNG CƯỜNG QUỐC PHÒNG, AN NINH, BẢO VỆ VỮNG CHẮC TỔ QUỐC VIỆT NAM XÃ HỘI CHỦ NGHĨA TRONG TÌNH HÌNH MỚI","slug":"bai-5-tang-cuong-quoc-phong-an-ninh-bao-ve-vung-chac-to-quoc-viet-nam-xa-hoi-chu-nghia-trong-tinh-hinh-moi","mo_ta":"BÀI 5","noi_dung":"<p>TĂNG CƯỜNG QUỐC PH&Ograve;NG, AN NINH, BẢO VỆ VỮNG CHẮC TỔ QUỐC VIỆT NAM X&Atilde; HỘI CHỦ NGHĨA TRONG T&Igrave;NH H&Igrave;NH MỚI</p>","thu_tu":0,"tags":["bai-giang-hsq-bs"],"photos":[],"attachments":[],"date_post":"2026-01-06 08:13:21","tin_moi":0,"id_user":{"$oid":"69533df1c2c912ac05084cde"},"updated_at":{"$date":"2026-01-06T01:14:27.076Z"},"created_at":{"$date":"2026-01-06T01:14:27.076Z"}}
{"_id":{"$oid":"695c633a9709dc3ea00d41bd"},"ten":"BÀI 6: XÂY DỰNG VÀ PHÁT HUY GIÁ TRỊ VĂN HÓA, SỨC MẠNH CON NGƯỜI VIỆT NAM","slug":"bai-6-xay-dung-va-phat-huy-gia-tri-van-hoa-suc-manh-con-nguoi-viet-nam","mo_ta":"BÀI 6","noi_dung":"<p>X&Acirc;Y DỰNG V&Agrave; PH&Aacute;T HUY GI&Aacute; TRỊ VĂN H&Oacute;A, SỨC MẠNH CON NGƯỜI VIỆT NAM</p>","thu_tu":0,"tags":["bai-giang-hsq-bs"],"photos":[],"attachments":[{"aliasname":"20260106081950_695c63364e1c1.pdf","filename":"Sơ đồ chữ bài 6.pdf","title":"Sơ đồ chữ bài 6.pdf","size":"495005","type":"pdf"}],"date_post":"2026-01-06 08:19:23","tin_moi":0,"id_user":{"$oid":"69533df1c2c912ac05084cde"},"updated_at":{"$date":"2026-01-06T01:19:54.804Z"},"created_at":{"$date":"2026-01-06T01:19:54.804Z"}}
{"_id":{"$oid":"695c63aa8e95c991830d3f3d"},"ten":"BÀI 7: ĐƯỜNG LỐI, CHÍNH SÁCH ĐỐI NGOẠI CỦA ĐẢNG, NHÀ NƯỚC TA HIỆN NAY","slug":"bai-7-duong-loi-chinh-sach-doi-ngoai-cua-dang-nha-nuoc-ta-hien-nay","mo_ta":"BÀI 7","noi_dung":"<p>ĐƯỜNG LỐI, CH&Iacute;NH S&Aacute;CH ĐỐI NGOẠI CỦA ĐẢNG, NH&Agrave; NƯỚC TA HIỆN NAY</p>","thu_tu":0,"tags":["bai-giang-hsq-bs"],"photos":[],"attachments":[{"aliasname":"20260106082144_695c63a8768e1.pdf","filename":"Sơ đồ chữ bài 7.pdf","title":"Sơ đồ chữ bài 7.pdf","size":"402686","type":"pdf"}],"date_post":"2026-01-06 08:21:21","tin_moi":0,"id_user":{"$oid":"69533df1c2c912ac05084cde"},"updated_at":{"$date":"2026-01-06T01:21:46.208Z"},"created_at":{"$date":"2026-01-06T01:21:46.208Z"}}
{"_id":{"$oid":"695c64157b143f547a0931c5"},"ten":"BÀI 8: XÂY DỰNG VÀ HOÀN THIỆN NHÀ NƯỚC PHÁP QUYỀN XÃ HỘI CHỦ NGHĨA VIỆT NAM","slug":"bai-8-xay-dung-va-hoan-thien-nha-nuoc-phap-quyen-xa-hoi-chu-nghia-viet-nam","mo_ta":"BÀI 8","noi_dung":"<p>X&Acirc;Y DỰNG V&Agrave; HO&Agrave;N THIỆN NH&Agrave; NƯỚC PH&Aacute;P QUYỀN X&Atilde; HỘI CHỦ NGHĨA VIỆT NAM</p>","thu_tu":0,"tags":["bai-giang-hsq-bs"],"photos":[],"attachments":[{"aliasname":"20260106082331_695c6413b064d.pdf","filename":"Sơ đồ chữ bài 8.pdf","title":"Sơ đồ chữ bài 8.pdf","size":"303254","type":"pdf"}],"date_post":"2026-01-06 08:23:08","tin_moi":0,"id_user":{"$oid":"69533df1c2c912ac05084cde"},"updated_at":{"$date":"2026-01-06T01:23:33.533Z"},"created_at":{"$date":"2026-01-06T01:23:33.533Z"}}
{"_id":{"$oid":"695c6e5a9709dc3ea00d41be"},"ten":"BÀI 10: ĐẤU TRANH LÀM THẤT BẠI ÂM MƯU, THỦ ĐOẠN “DIỄN BIẾN HÒA BÌNH” CỦA CÁC THẾ LỰC THÙ ĐỊCH CHỐNG PHÁ CÁCH MẠNG VIỆT NAM HIỆN NAY","slug":"bai-10-dau-tranh-lam-that-bai-am-muu-thu-doan-dien-bien-hoa-binh-cua-cac-the-luc-thu-dich-chong-pha-cach-mang-viet-nam-hien-nay","mo_ta":"BÀI 10","noi_dung":"<p>ĐẤU TRANH L&Agrave;M THẤT BẠI &Acirc;M MƯU, THỦ ĐOẠN &ldquo;DIỄN BIẾN H&Ograve;A B&Igrave;NH&rdquo; CỦA C&Aacute;C THẾ LỰC TH&Ugrave; ĐỊCH<br />\r\nCHỐNG PH&Aacute; C&Aacute;CH MẠNG VIỆT NAM HIỆN NAY</p>","thu_tu":0,"tags":["bai-giang-hsq-bs"],"photos":[],"attachments":[{"aliasname":"20260106090719_695c6e5712ee4.pdf","filename":"Sơ đồ chữ bài 10.pdf","title":"Sơ đồ chữ bài 10.pdf","size":"364332","type":"pdf"}],"date_post":"2026-01-06 09:06:47","tin_moi":0,"id_user":{"$oid":"69533df1c2c912ac05084cde"},"updated_at":{"$date":"2026-01-06T02:07:22.728Z"},"created_at":{"$date":"2026-01-06T02:07:22.728Z"}}
{"_id":{"$oid":"695c7bdb50841405ef0ff637"},"ten":"ĐỀ ÁN 1371","slug":"de-an-1371","mo_ta":"Đề án 1371","noi_dung":"<p>Ph&aacute;t huy vai tr&ograve; của lực lượng Qu&acirc;n đội nh&acirc;n d&acirc;n tham gia c&ocirc;ng t&aacute;c phổ biến, gi&aacute;o dục ph&aacute;p luật, vận động Nh&acirc;n</p>","thu_tu":0,"tags":["cac-van-ban-quy-dinh-pbpl"],"photos":[],"attachments":[],"date_post":"2026-01-06 10:03:53","tin_moi":0,"id_user":{"$oid":"69533df1c2c912ac05084cde"},"updated_at":{"$date":"2026-01-06T03:04:59.187Z"},"created_at":{"$date":"2026-01-06T03:04:59.187Z"}}
{"_id":{"$oid":"695c7d10e08e4f2a8e015a89"},"ten":"TÀI LIỆU BỒI DƯỠNG NHẬN THỨC VỀ ĐẢNG DÀNH CHO ĐỐI TƯỢNG KẾT NẠP ĐẢNG","slug":"tai-lieu-boi-duong-nhan-thuc-ve-dang-danh-cho-doi-tuong-ket-nap-dang","mo_ta":"TÀI LIỆU","noi_dung":"<p>BỒI DƯỠNG NHẬN THỨC VỀ ĐẢNG D&Agrave;NH CHO ĐỐI TƯỢNG KẾT NẠP ĐẢNG</p>","thu_tu":0,"tags":["bai-giang-dang-vien"],"photos":[],"attachments":[],"date_post":"2026-01-06 10:09:18","tin_moi":0,"id_user":{"$oid":"69533df1c2c912ac05084cde"},"updated_at":{"$date":"2026-01-06T03:10:08.607Z"},"created_at":{"$date":"2026-01-06T03:10:08.607Z"}}
{"_id":{"$oid":"695cb236889b713845017106"},"ten":"Chỉ thị 2423-CT/QUTW","slug":"chi-thi-2423","mo_ta":"Chỉ thị 2423-CT/QUTW","noi_dung":"<p>Về đổi mới, n&acirc;ng cao chất lượng c&ocirc;ng t&aacute;c gi&aacute;o dục ch&iacute;nh trị trong giai đoạn mới</p>","thu_tu":0,"tags":["cac-van-ban-quy-dinh-gdctcb"],"photos":[],"attachments":[{"aliasname":"20260106135649_695cb2315f148.pdf","filename":"Chỉ thị 2423- Đổi mới GDCT 2023.pdf","title":"Chỉ thị 2423- Đổi mới GDCT 2023.pdf","size":"347138","type":"pdf"}],"date_post":"2026-01-06 13:48:40","tin_moi":0,"id_user":{"$oid":"69533df1c2c912ac05084cde"},"updated_at":{"$date":"2026-01-06T06:56:54.447Z"},"created_at":{"$date":"2026-01-06T06:56:54.447Z"}}
{"_id":{"$oid":"695cb86192f0721f160ec59f"},"ten":"Đề cương tuyên truyền Kỷ niệm 81 năm Ngày thành lập Quân đội nhân dân Việt Nam và 36 năm Ngày hội Quốc phòng toàn dân","slug":"de-cuong-tuyen-truyen-ky-niem-81-nam-ngay-thanh-lap-quan-doi-nhan-dan-viet-nam-va-36-nam-ngay-hoi-quoc-phong-toan-dan","mo_ta":"Đề cương tuyên truyền","noi_dung":"<p>Kỷ niệm 81 năm Ng&agrave;y th&agrave;nh lập Qu&acirc;n đội nh&acirc;n d&acirc;n Việt Nam (22/12/1944 - 22/12/2025) v&agrave; 36 năm Ng&agrave;y hội Quốc ph&ograve;ng to&agrave;n d&acirc;n (22/12/1989 - 22/12/2025)</p>","thu_tu":0,"tags":["de-cuong-tuyen-truyen","truyen-thong-quan-doi"],"photos":[],"attachments":[{"aliasname":"20260106142212_695cb824c2300.pdf","filename":"ĐỀ CƯƠNG TUYÊN TRUYỀN KỶ NIỆM 81 NĂM NGÀY THÀNH LẬP QUÂN ĐỘI NHÂN DÂN VIỆT NAM VÀ 35 NĂM NGÀY HỘI QUỐC PHÒNG TOÀN DÂN I.pdf","title":"ĐỀ CƯƠNG TUYÊN TRUYỀN KỶ NIỆM 81 NĂM NGÀY THÀNH LẬP QUÂN ĐỘI NHÂN DÂN VIỆT NAM VÀ 35 NĂM NGÀY HỘI QUỐC PHÒNG TOÀN DÂN I.pdf","size":"320896","type":"pdf"}],"date_post":"2026-01-06 14:22:03","tin_moi":0,"id_user":{"$oid":"69533df1c2c912ac05084cde"},"updated_at":{"$date":"2026-01-06T07:23:13.278Z"},"created_at":{"$date":"2026-01-06T07:23:13.278Z"}}
{"_id":{"$oid":"695cb8ec5b90d9b42203ab91"},"ten":"CHUYÊN ĐỀ TỰ HÀO PHÁT HUY TRUYỀN THỐNG 80 NĂM XÂY DỰNG, CHIẾN ĐẤU, TRƯỞNG THÀNH CỦA LỰC LƯỢNG VŨ TRANG QUÂN KHU 9","slug":"chuyen-de-tu-hao-phat-huy-truyen-thong-80-nam-xay-dung-chien-dau-truong-thanh-cua-luc-luong-vu-trang-quan-khu-9","mo_ta":"CHUYÊN ĐỀ","noi_dung":"<p>TỰ H&Agrave;O PH&Aacute;T HUY TRUYỀN THỐNG 80 NĂM X&Acirc;Y DỰNG, CHIẾN ĐẤU, TRƯỞNG TH&Agrave;NH CỦA LỰC LƯỢNG VŨ TRANG QU&Acirc;N KHU 9&nbsp;</p>","thu_tu":0,"tags":["de-cuong-tuyen-truyen","truyen-thong-quan-doi"],"photos":[],"attachments":[{"aliasname":"20260106142444_695cb8bc0d8e4.pdf","filename":"CĐ TỰ HÀO TRUYỀN THỐNG 80 NĂM LLVT QK.pdf","title":"CĐ TỰ HÀO TRUYỀN THỐNG 80 NĂM LLVT QK.pdf","size":"1025036","type":"pdf"}],"date_post":"2026-01-06 14:24:37","tin_moi":0,"id_user":{"$oid":"69533df1c2c912ac05084cde"},"updated_at":{"$date":"2026-01-06T07:25:32.344Z"},"created_at":{"$date":"2026-01-06T07:25:32.344Z"}}
{"_id":{"$oid":"695cc1ec0b0e0369f00ab65e"},"ten":"LỜI HỨA ĐIỆN BIÊN","slug":"loi-hua-dien-bien","mo_ta":"Phim Hoạt Hình 2D Lịch Sử Việt Nam Hay Nhất 2025","noi_dung":"<p style=\"text-align: center;\"><iframe frameborder=\"0\" height=\"480\" scrolling=\"no\" src=\"https://www.youtube.com/embed/OG2ZLqrT7IY?si=UEqvCe27vrPwEBh0\" width=\"640\"></iframe></p>","thu_tu":0,"tags":["truyen-thong-quan-doi"],"photos":[],"attachments":[],"date_post":"2026-01-06 15:02:14","tin_moi":0,"id_user":{"$oid":"69533df1c2c912ac05084cde"},"updated_at":{"$date":"2026-01-06T08:03:56.029Z"},"created_at":{"$date":"2026-01-06T08:03:56.029Z"}}
{"_id":{"$oid":"695cc2e1889b713845017107"},"ten":"Cuộc kháng chiến chống quân Nguyên Mông năm 1285 của nhà Trần, Đại Chiến 3 cánh quân","slug":"cuoc-khang-chien-chong-quan-nguyen-mong-nam-1285-cua-nha-tran-dai-chien-3-canh-quan","mo_ta":"Phim hoạt hình lịch sử","noi_dung":"<p style=\"text-align: center;\"><iframe frameborder=\"0\" height=\"480\" scrolling=\"no\" src=\"https://www.youtube.com/embed/Z3DYGD6848s?si=E4MsraTb4yCxdxi-\" width=\"640\"></iframe></p>","thu_tu":0,"tags":["truyen-thong-dan-toc"],"photos":[],"attachments":[],"date_post":"2026-01-06 15:06:19","tin_moi":0,"id_user":{"$oid":"69533df1c2c912ac05084cde"},"updated_at":{"$date":"2026-01-06T08:08:01.966Z"},"created_at":{"$date":"2026-01-06T08:08:01.966Z"}}
{"_id":{"$oid":"695f14b30ba519f2c60ea108"},"ten":"Người Anh Hùng Áo Vải","slug":"nguoi-anh-hung-ao-vai","mo_ta":"Phim Hoạt Hình Lịch Sử Việt Nam","noi_dung":"<p style=\"text-align: center;\"><iframe frameborder=\"0\" height=\"480\" scrolling=\"no\" src=\"https://www.youtube.com/embed/mqsiVF8qCag?si=Hmf99UNlY12Zwyn9&quot; title=&quot;YouTube video player\" width=\"640\"></iframe></p>","thu_tu":0,"tags":["truyen-thong-dan-toc"],"photos":[],"attachments":[],"date_post":"2026-01-08 09:20:33","tin_moi":0,"id_user":{"$oid":"69533df1c2c912ac05084cde"},"updated_at":{"$date":"2026-01-08T02:21:39.669Z"},"created_at":{"$date":"2026-01-08T02:21:39.669Z"}}
{"_id":{"$oid":"695f15f7889b713845017108"},"ten":"Trận thuỷ chiến huyền thoại, Bạch Đằng Giang rực lửa. Quân Nguyên thảm bại. Thắng lợi của nhà Trần","slug":"tran-thuy-chien-huyen-thoai-bach-dang-giang-ruc-lua-quan-nguyen-tham-bai-thang-loi-cua-nha-tran","mo_ta":"Phim hoạt hình lịch sử","noi_dung":"<p style=\"text-align: center;\"><iframe frameborder=\"0\" height=\"480\" scrolling=\"no\" src=\"https://www.youtube.com/embed/tfWgCrPdlKQ?si=K5bQ2KfdMconOiLv\" width=\"640\"></iframe></p>","thu_tu":0,"tags":["truyen-thong-dan-toc"],"photos":[],"attachments":[],"date_post":"2026-01-08 09:25:52","tin_moi":0,"id_user":{"$oid":"69533df1c2c912ac05084cde"},"updated_at":{"$date":"2026-01-08T02:27:03.505Z"},"created_at":{"$date":"2026-01-08T02:27:03.505Z"}}
{"_id":{"$oid":"695f171be08e4f2a8e015a8a"},"ten":"Quân Trần giả hàng, tập kích đại bản doanh Lục Đầu, Ô Mã Nhi bị vây hãm tại Bạch Đằng,","slug":"quan-tran-gia-hang-tap-kich-dai-ban-doanh-luc-dau-o-ma-nhi-bi-vay-ham-tai-bach-dang","mo_ta":"Phim hoạt hình lịch sử","noi_dung":"<p style=\"text-align: center;\"><iframe frameborder=\"0\" height=\"480\" scrolling=\"no\" src=\"https://www.youtube.com/embed/T-_bTPkOOzY?si=llYmo279yjNHcbxj&quot; title=&quot;YouTube video player\" width=\"640\"></iframe></p>","thu_tu":0,"tags":["truyen-thong-dan-toc"],"photos":[],"attachments":[],"date_post":"2026-01-08 09:30:45","tin_moi":0,"id_user":{"$oid":"69533df1c2c912ac05084cde"},"updated_at":{"$date":"2026-01-08T02:31:55.186Z"},"created_at":{"$date":"2026-01-08T02:31:55.186Z"}}
{"_id":{"$oid":"695f17750b0e0369f00ab65f"},"ten":"Hành Trình Đi Tìm Đường Cứu Nước Của Nguyễn Ái Quốc","slug":"hanh-trinh-di-tim-duong-cuu-nuoc-cua-nguyen-ai-quoc","mo_ta":"Phim hoạt hình lịch sử","noi_dung":"<p style=\"text-align: center;\"><iframe frameborder=\"0\" height=\"480\" scrolling=\"no\" src=\"https://www.youtube.com/embed/Qu3yMoQfWXI?si=OgCHY6HglqE8t8VJ\" width=\"640\"></iframe></p>","thu_tu":0,"tags":["truyen-thong-dan-toc"],"photos":[],"attachments":[],"date_post":"2026-01-08 09:32:32","tin_moi":0,"id_user":{"$oid":"69533df1c2c912ac05084cde"},"updated_at":{"$date":"2026-01-08T02:33:25.126Z"},"created_at":{"$date":"2026-01-08T02:33:25.126Z"}}
{"_id":{"$oid":"695f18599709dc3ea00d41bf"},"ten":"Tham quan khu lưu niệm Chủ tịch Tôn Đức Thắng","slug":"tham-quan-khu-luu-niem-chu-tich-ton-duc-thang","mo_ta":"Bấm vào đường Link để tham quan online Khu lưu niệm Chủ tịch Tôn Đức Thắng","noi_dung":"<p><a href=\"https://www.agu.edu.vn/tonducthang/3dvr/\">https://www.agu.edu.vn/tonducthang/3dvr/</a></p>","thu_tu":0,"tags":["truyen-thong-dan-toc"],"photos":[],"attachments":[],"date_post":"2026-01-08 09:34:22","tin_moi":0,"id_user":{"$oid":"69533df1c2c912ac05084cde"},"updated_at":{"$date":"2026-01-08T02:37:13.587Z"},"created_at":{"$date":"2026-01-08T02:37:13.587Z"}}
