{"_id":{"$oid":"6790563aa427ba20170fb8f2"},"ma":"6790563A634E0","nganhnghe_id":{"$oid":"67847d733fcf3499e709ee17"},"noi_dung":[{"noi_dung":"<p>Xin ch&agrave;o ch&agrave;o...</p>","id_user":{"$oid":"5d4837cb4d9fb92758005066"}}],"id_user":{"$oid":"5d4837cb4d9fb92758005066"},"tinh_trang":1,"updated_at":{"$date":"2025-01-22T03:27:02.318Z"},"created_at":{"$date":"2025-01-22T02:21:46.407Z"}}
{"_id":{"$oid":"679056fca427ba20170fb8f5"},"ma":"679056FC75594","nganhnghe_id":{"$oid":"67847d733fcf3499e709ee17"},"noi_dung":[{"noi_dung":"<p>Cho hỏi về chuyển đổi số lĩnh Vực gi&aacute;o dục.</p>","id_user":{"$oid":"678f5321a427ba20170fb8e5"}},{"noi_dung":"<p>Trả lời nội dung tr&ecirc;n như sau:&nbsp;</p>\r\n\r\n<p>1. ABC</p>\r\n\r\n<p>2. BDEF</p>","id_user":{"$oid":"678f5321a427ba20170fb8e5"}},{"noi_dung":"<p>Ch&uacute;ng t&ocirc;i trả lời anh chị như sau~</p>","id_user":{"$oid":"5d4837cb4d9fb92758005066"}},{"noi_dung":"<p>Ok vậy l&agrave; chuẩn s&aacute;t</p>","id_user":{"$oid":"678f5321a427ba20170fb8e5"}},{"noi_dung":"<p>t56k347</p>\r\n\r\n<p>&nbsp;</p>","id_user":{"$oid":"5d4837cb4d9fb92758005066"}}],"id_user":{"$oid":"678f5321a427ba20170fb8e5"},"tinh_trang":0,"updated_at":{"$date":"2025-01-22T02:25:00.481Z"},"created_at":{"$date":"2025-01-22T02:25:00.481Z"}}
{"_id":{"$oid":"6791f64da427ba20170fb90a"},"ma":"6791F64D5C3FD","nganhnghe_id":{"$oid":"67847d733fcf3499e709ee17"},"noi_dung":[{"noi_dung":"<p>C&acirc;u hỏi</p>","id_user":{"$oid":"678f5e8da427ba20170fb8ee"}}],"id_user":{"$oid":"678f5e8da427ba20170fb8ee"},"tinh_trang":1,"updated_at":{"$date":"2025-01-23T07:58:19.415Z"},"created_at":{"$date":"2025-01-23T07:57:01.378Z"}}
